{"pluginVersion":"1.0.0","bounds":{"top":0,"left":0,"bottom":1350,"right":1000},"sprites":[{"id":102,"name":"Group_4","bounds":{"top":634,"left":0,"bottom":1331,"right":988},"visible":true,"sprites":[{"id":101,"name":"Line_2_Group_4","bounds":{"top":634,"left":0,"bottom":1331,"right":988},"visible":true,"sprites":null},{"id":86,"name":"Group_4_15","bounds":{"top":900,"left":331,"bottom":929,"right":401},"visible":true,"sprites":null},{"id":85,"name":"Group_4_14","bounds":{"top":1151,"left":819,"bottom":1180,"right":889},"visible":true,"sprites":null},{"id":84,"name":"Group_4_13","bounds":{"top":1213,"left":0,"bottom":1245,"right":86},"visible":true,"sprites":null},{"id":83,"name":"Group_4_12","bounds":{"top":1294,"left":497,"bottom":1325,"right":588},"visible":true,"sprites":null},{"id":82,"name":"Group_4_11","bounds":{"top":1104,"left":592,"bottom":1135,"right":684},"visible":true,"sprites":null},{"id":81,"name":"Group_4_10","bounds":{"top":1280,"left":917,"bottom":1312,"right":982},"visible":true,"sprites":null},{"id":80,"name":"Group_4_9","bounds":{"top":1012,"left":575,"bottom":1053,"right":640},"visible":true,"sprites":null},{"id":79,"name":"Group_4_8","bounds":{"top":640,"left":569,"bottom":974,"right":671},"visible":true,"sprites":null},{"id":78,"name":"Group_4_7","bounds":{"top":845,"left":111,"bottom":1179,"right":212},"visible":true,"sprites":null},{"id":77,"name":"Group_4_6","bounds":{"top":1003,"left":139,"bottom":1073,"right":247},"visible":true,"sprites":null},{"id":106,"name":"Line_1_Group_4","bounds":{"top":867,"left":9,"bottom":1100,"right":290},"visible":true,"sprites":null},{"id":76,"name":"Group_4_5","bounds":{"top":873,"left":58,"bottom":963,"right":95},"visible":true,"sprites":null},{"id":75,"name":"Group_4_4","bounds":{"top":1026,"left":75,"bottom":1088,"right":108},"visible":true,"sprites":null},{"id":73,"name":"Group_4_3","bounds":{"top":979,"left":15,"bottom":1094,"right":129},"visible":true,"sprites":null},{"id":69,"name":"Group_4_2","bounds":{"top":921,"left":122,"bottom":1094,"right":284},"visible":true,"sprites":null},{"id":65,"name":"Group_4_1","bounds":{"top":1021,"left":37,"bottom":1057,"right":58},"visible":true,"sprites":null}]},{"id":104,"name":"Group_3","bounds":{"top":836,"left":15,"bottom":1311,"right":1000},"visible":true,"sprites":[{"id":99,"name":"Line_2_Group_3","bounds":{"top":836,"left":15,"bottom":1311,"right":485},"visible":true,"sprites":null},{"id":63,"name":"Group_3_13","bounds":{"top":842,"left":21,"bottom":1088,"right":133},"visible":true,"sprites":null},{"id":60,"name":"Group_3_12","bounds":{"top":1223,"left":352,"bottom":1261,"right":385},"visible":true,"sprites":null},{"id":59,"name":"Group_3_11","bounds":{"top":1170,"left":331,"bottom":1305,"right":479},"visible":true,"sprites":null},{"id":58,"name":"Group_3_10","bounds":{"top":1081,"left":242,"bottom":1161,"right":473},"visible":true,"sprites":null},{"id":57,"name":"Group_3_9","bounds":{"top":1230,"left":408,"bottom":1305,"right":451},"visible":true,"sprites":null},{"id":56,"name":"Group_3_8","bounds":{"top":1190,"left":279,"bottom":1289,"right":318},"visible":true,"sprites":null},{"id":98,"name":"Line_1_Group_3","bounds":{"top":974,"left":248,"bottom":1311,"right":1000},"visible":true,"sprites":null},{"id":55,"name":"Group_3_7","bounds":{"top":1160,"left":254,"bottom":1305,"right":461},"visible":true,"sprites":null},{"id":54,"name":"Group_3_6","bounds":{"top":1007,"left":878,"bottom":1271,"right":1000},"visible":true,"sprites":null},{"id":52,"name":"Group_3_5","bounds":{"top":987,"left":858,"bottom":1032,"right":906},"visible":true,"sprites":null},{"id":46,"name":"Group_3_4","bounds":{"top":1062,"left":778,"bottom":1141,"right":818},"visible":true,"sprites":null},{"id":45,"name":"Group_3_3","bounds":{"top":980,"left":783,"bottom":1044,"right":814},"visible":true,"sprites":null},{"id":44,"name":"Group_3_2","bounds":{"top":1012,"left":713,"bottom":1118,"right":744},"visible":true,"sprites":null},{"id":38,"name":"Group_3_1","bounds":{"top":1073,"left":849,"bottom":1128,"right":935},"visible":true,"sprites":null}]},{"id":96,"name":"Group_2","bounds":{"top":399,"left":208,"bottom":1277,"right":971},"visible":true,"sprites":[{"id":95,"name":"Line_3_Group_2","bounds":{"top":483,"left":208,"bottom":1277,"right":971},"visible":true,"sprites":null},{"id":42,"name":"Group_2_10","bounds":{"top":951,"left":686,"bottom":1141,"right":844},"visible":true,"sprites":null},{"id":36,"name":"Group_2_9","bounds":{"top":1025,"left":835,"bottom":1141,"right":965},"visible":true,"sprites":null},{"id":33,"name":"Group_2_8","bounds":{"top":1007,"left":448,"bottom":1271,"right":570},"visible":true,"sprites":null},{"id":32,"name":"Group_2_7","bounds":{"top":749,"left":214,"bottom":1013,"right":336},"visible":true,"sprites":null},{"id":31,"name":"Group_2_6","bounds":{"top":877,"left":325,"bottom":1271,"right":485},"visible":true,"sprites":null},{"id":30,"name":"Group_2_5","bounds":{"top":489,"left":529,"bottom":666,"right":540},"visible":true,"sprites":null},{"id":94,"name":"Line_2_Group_2","bounds":{"top":399,"left":430,"bottom":888,"right":591},"visible":true,"sprites":null},{"id":29,"name":"Group_2_4","bounds":{"top":405,"left":485,"bottom":689,"right":547},"visible":true,"sprites":null},{"id":28,"name":"Group_2_3","bounds":{"top":750,"left":523,"bottom":841,"right":585},"visible":true,"sprites":null},{"id":27,"name":"Group_2_2","bounds":{"top":715,"left":436,"bottom":882,"right":484},"visible":true,"sprites":null},{"id":93,"name":"Line_1_Group_2","bounds":{"top":661,"left":407,"bottom":888,"right":612},"visible":true,"sprites":null},{"id":26,"name":"Group_2_1","bounds":{"top":667,"left":413,"bottom":882,"right":606},"visible":true,"sprites":null}]},{"id":91,"name":"Group_1","bounds":{"top":0,"left":0,"bottom":1350,"right":1000},"visible":true,"sprites":[{"id":90,"name":"Line_2_Group_1","bounds":{"top":809,"left":0,"bottom":1350,"right":1000},"visible":true,"sprites":null},{"id":25,"name":"Group_1_10","bounds":{"top":841,"left":0,"bottom":1350,"right":1000},"visible":true,"sprites":null},{"id":24,"name":"Group_1_9","bounds":{"top":815,"left":0,"bottom":1050,"right":401},"visible":true,"sprites":null},{"id":23,"name":"Group_1_8","bounds":{"top":852,"left":612,"bottom":1038,"right":919},"visible":true,"sprites":null},{"id":89,"name":"Line_1_Group_1","bounds":{"top":128,"left":0,"bottom":1075,"right":1000},"visible":true,"sprites":null},{"id":22,"name":"Group_1_7","bounds":{"top":364,"left":122,"bottom":995,"right":406},"visible":true,"sprites":null},{"id":21,"name":"Group_1_6","bounds":{"top":350,"left":493,"bottom":949,"right":825},"visible":true,"sprites":null},{"id":20,"name":"Group_1_5","bounds":{"top":186,"left":301,"bottom":892,"right":522},"visible":true,"sprites":null},{"id":19,"name":"Group_1_4","bounds":{"top":595,"left":741,"bottom":1069,"right":961},"visible":true,"sprites":null},{"id":8,"name":"Group_1_3","bounds":{"top":134,"left":813,"bottom":175,"right":1000},"visible":true,"sprites":null},{"id":7,"name":"Group_1_2","bounds":{"top":219,"left":0,"bottom":257,"right":160},"visible":true,"sprites":null},{"id":6,"name":"Group_1_1","bounds":{"top":322,"left":0,"bottom":388,"right":409},"visible":true,"sprites":null},{"id":4,"name":"Background","bounds":{"top":0,"left":0,"bottom":1348,"right":1000},"visible":true,"sprites":null}]}]}