{"pluginVersion":"1.0.0","bounds":{"top":0,"left":0,"bottom":1350,"right":1000},"sprites":[{"id":137,"name":"Group_3","bounds":{"top":746,"left":424,"bottom":1297,"right":988},"visible":true,"sprites":[{"id":136,"name":"Line_2_Group_3","bounds":{"top":772,"left":592,"bottom":1297,"right":986},"visible":true,"sprites":null},{"id":122,"name":"Group_3_13","bounds":{"top":1168,"left":597,"bottom":1292,"right":728},"visible":true,"sprites":null},{"id":119,"name":"Group_3_12","bounds":{"top":1104,"left":810,"bottom":1210,"right":981},"visible":true,"sprites":null},{"id":118,"name":"Group_3_11","bounds":{"top":1070,"left":639,"bottom":1158,"right":777},"visible":true,"sprites":null},{"id":116,"name":"Group_3_10","bounds":{"top":777,"left":807,"bottom":852,"right":889},"visible":true,"sprites":null},{"id":135,"name":"Line_1_Group_3","bounds":{"top":746,"left":424,"bottom":1221,"right":988},"visible":true,"sprites":null},{"id":107,"name":"Group_3_9","bounds":{"top":816,"left":841,"bottom":930,"right":984},"visible":true,"sprites":null},{"id":105,"name":"Group_3_8","bounds":{"top":872,"left":731,"bottom":914,"right":779},"visible":true,"sprites":null},{"id":98,"name":"Group_3_7","bounds":{"top":830,"left":752,"bottom":873,"right":799},"visible":true,"sprites":null},{"id":91,"name":"Group_3_6","bounds":{"top":808,"left":628,"bottom":897,"right":726},"visible":true,"sprites":null},{"id":84,"name":"Group_3_5","bounds":{"top":756,"left":603,"bottom":805,"right":648},"visible":true,"sprites":null},{"id":77,"name":"Group_3_4","bounds":{"top":750,"left":508,"bottom":855,"right":606},"visible":true,"sprites":null},{"id":71,"name":"Group_3_3","bounds":{"top":944,"left":428,"bottom":1017,"right":527},"visible":true,"sprites":null},{"id":69,"name":"Group_3_2","bounds":{"top":1012,"left":428,"bottom":1217,"right":573},"visible":true,"sprites":null},{"id":55,"name":"Group_3_1","bounds":{"top":971,"left":550,"bottom":1196,"right":591},"visible":true,"sprites":null}]},{"id":133,"name":"Group_2","bounds":{"top":589,"left":0,"bottom":1179,"right":932},"visible":true,"sprites":[{"id":132,"name":"Line_2_Group_2","bounds":{"top":982,"left":45,"bottom":1173,"right":591},"visible":true,"sprites":null},{"id":54,"name":"Group_2_20","bounds":{"top":1104,"left":344,"bottom":1169,"right":587},"visible":true,"sprites":null},{"id":53,"name":"Group_2_19","bounds":{"top":1084,"left":50,"bottom":1169,"right":136},"visible":true,"sprites":null},{"id":52,"name":"Group_2_18","bounds":{"top":1049,"left":191,"bottom":1169,"right":311},"visible":true,"sprites":null},{"id":51,"name":"Group_2_17","bounds":{"top":1042,"left":49,"bottom":1133,"right":315},"visible":true,"sprites":null},{"id":50,"name":"Group_2_16","bounds":{"top":986,"left":167,"bottom":1059,"right":277},"visible":true,"sprites":null},{"id":131,"name":"Line_1_Group_2","bounds":{"top":589,"left":0,"bottom":1179,"right":932},"visible":true,"sprites":null},{"id":48,"name":"Group_2_15","bounds":{"top":977,"left":77,"bottom":1128,"right":288},"visible":true,"sprites":null},{"id":44,"name":"Group_2_14","bounds":{"top":967,"left":95,"bottom":1064,"right":165},"visible":true,"sprites":null},{"id":43,"name":"Group_2_13","bounds":{"top":1029,"left":293,"bottom":1128,"right":594},"visible":true,"sprites":null},{"id":42,"name":"Group_2_12","bounds":{"top":1149,"left":47,"bottom":1174,"right":614},"visible":true,"sprites":null},{"id":41,"name":"Group_2_11","bounds":{"top":967,"left":344,"bottom":1105,"right":490},"visible":true,"sprites":null},{"id":40,"name":"Group_2_10","bounds":{"top":967,"left":491,"bottom":1105,"right":588},"visible":true,"sprites":null},{"id":39,"name":"Group_2_9","bounds":{"top":990,"left":851,"bottom":1030,"right":927},"visible":true,"sprites":null},{"id":38,"name":"Group_2_8","bounds":{"top":933,"left":692,"bottom":1019,"right":857},"visible":true,"sprites":null},{"id":37,"name":"Group_2_7","bounds":{"top":888,"left":631,"bottom":949,"right":680},"visible":true,"sprites":null},{"id":36,"name":"Group_2_6","bounds":{"top":870,"left":544,"bottom":949,"right":626},"visible":true,"sprites":null},{"id":35,"name":"Group_2_5","bounds":{"top":932,"left":567,"bottom":955,"right":672},"visible":true,"sprites":null},{"id":34,"name":"Group_2_4","bounds":{"top":611,"left":496,"bottom":672,"right":566},"visible":true,"sprites":null},{"id":33,"name":"Group_2_3","bounds":{"top":594,"left":565,"bottom":682,"right":667},"visible":true,"sprites":null},{"id":32,"name":"Group_2_2","bounds":{"top":958,"left":0,"bottom":995,"right":88},"visible":true,"sprites":null},{"id":31,"name":"Group_2_1","bounds":{"top":951,"left":65,"bottom":998,"right":138},"visible":true,"sprites":null}]},{"id":129,"name":"Group_1","bounds":{"top":0,"left":0,"bottom":1350,"right":1000},"visible":true,"sprites":[{"id":128,"name":"Line_2_Group_1","bounds":{"top":782,"left":57,"bottom":989,"right":435},"visible":true,"sprites":null},{"id":30,"name":"Group_1_19","bounds":{"top":786,"left":175,"bottom":827,"right":295},"visible":true,"sprites":null},{"id":29,"name":"Group_1_18","bounds":{"top":901,"left":126,"bottom":942,"right":157},"visible":true,"sprites":null},{"id":28,"name":"Group_1_17","bounds":{"top":901,"left":322,"bottom":942,"right":353},"visible":true,"sprites":null},{"id":27,"name":"Group_1_16","bounds":{"top":862,"left":199,"bottom":985,"right":288},"visible":true,"sprites":null},{"id":25,"name":"Group_1_15","bounds":{"top":829,"left":61,"bottom":886,"right":154},"visible":true,"sprites":null},{"id":21,"name":"Group_1_14","bounds":{"top":829,"left":338,"bottom":886,"right":431},"visible":true,"sprites":null},{"id":126,"name":"Line_1_Group_1","bounds":{"top":108,"left":3,"bottom":990,"right":986},"visible":true,"sprites":null},{"id":17,"name":"Group_1_13","bounds":{"top":681,"left":95,"bottom":772,"right":397},"visible":true,"sprites":null},{"id":14,"name":"Group_1_12","bounds":{"top":692,"left":134,"bottom":844,"right":358},"visible":true,"sprites":null},{"id":13,"name":"Group_1_11","bounds":{"top":829,"left":87,"bottom":985,"right":400},"visible":true,"sprites":null},{"id":12,"name":"Group_1_10","bounds":{"top":800,"left":378,"bottom":976,"right":500},"visible":true,"sprites":null},{"id":11,"name":"Group_1_9","bounds":{"top":800,"left":8,"bottom":976,"right":130},"visible":true,"sprites":null},{"id":10,"name":"Group_1_8","bounds":{"top":704,"left":938,"bottom":829,"right":981},"visible":true,"sprites":null},{"id":9,"name":"Group_1_7","bounds":{"top":694,"left":886,"bottom":820,"right":929},"visible":true,"sprites":null},{"id":8,"name":"Group_1_6","bounds":{"top":682,"left":826,"bottom":807,"right":867},"visible":true,"sprites":null},{"id":7,"name":"Group_1_5","bounds":{"top":674,"left":475,"bottom":799,"right":518},"visible":true,"sprites":null},{"id":6,"name":"Group_1_4","bounds":{"top":620,"left":61,"bottom":745,"right":104},"visible":true,"sprites":null},{"id":5,"name":"Group_1_3","bounds":{"top":620,"left":16,"bottom":745,"right":59},"visible":true,"sprites":null},{"id":4,"name":"Group_1_2","bounds":{"top":694,"left":387,"bottom":820,"right":429},"visible":true,"sprites":null},{"id":3,"name":"Group_1_1","bounds":{"top":113,"left":15,"bottom":494,"right":958},"visible":true,"sprites":null},{"id":2,"name":"Background","bounds":{"top":0,"left":0,"bottom":1350,"right":1000},"visible":true,"sprites":null}]}]}