{"frames": [

{
	"filename": "woman_arms_big_2.png",
	"frame": {"x":1101,"y":1483,"w":559,"h":409},
	"rotated": false,
	"trimmed": false,
	"spriteSourceSize": {"x":0,"y":0,"w":559,"h":409},
	"sourceSize": {"w":559,"h":409}
},
{
	"filename": "woman_arms_big_15.png",
	"frame": {"x":1101,"y":991,"w":552,"h":490},
	"rotated": false,
	"trimmed": false,
	"spriteSourceSize": {"x":0,"y":0,"w":552,"h":490},
	"sourceSize": {"w":552,"h":490}
},
{
	"filename": "woman_body_big_6.png",
	"frame": {"x":1585,"y":489,"w":271,"h":417},
	"rotated": false,
	"trimmed": false,
	"spriteSourceSize": {"x":0,"y":0,"w":271,"h":417},
	"sourceSize": {"w":271,"h":417}
},
{
	"filename": "woman_body_big_23.png",
	"frame": {"x":1655,"y":908,"w":248,"h":388},
	"rotated": false,
	"trimmed": false,
	"spriteSourceSize": {"x":0,"y":0,"w":248,"h":388},
	"sourceSize": {"w":248,"h":388}
},
{
	"filename": "woman_body_big_26.png",
	"frame": {"x":1585,"y":1,"w":302,"h":486},
	"rotated": false,
	"trimmed": false,
	"spriteSourceSize": {"x":0,"y":0,"w":302,"h":486},
	"sourceSize": {"w":302,"h":486}
},
{
	"filename": "woman_head_big_1.png",
	"frame": {"x":1662,"y":1668,"w":348,"h":295},
	"rotated": false,
	"trimmed": false,
	"spriteSourceSize": {"x":0,"y":0,"w":348,"h":295},
	"sourceSize": {"w":348,"h":295}
},
{
	"filename": "woman_head_big_3.png",
	"frame": {"x":1858,"y":489,"w":170,"h":322},
	"rotated": false,
	"trimmed": false,
	"spriteSourceSize": {"x":0,"y":0,"w":170,"h":322},
	"sourceSize": {"w":170,"h":322}
},
{
	"filename": "woman_head_big_7.png",
	"frame": {"x":1873,"y":1298,"w":161,"h":343},
	"rotated": false,
	"trimmed": false,
	"spriteSourceSize": {"x":0,"y":0,"w":161,"h":343},
	"sourceSize": {"w":161,"h":343}
},
{
	"filename": "woman_head_big_25.png",
	"frame": {"x":1662,"y":1298,"w":209,"h":368},
	"rotated": false,
	"trimmed": false,
	"spriteSourceSize": {"x":0,"y":0,"w":209,"h":368},
	"sourceSize": {"w":209,"h":368}
},
{
	"filename": "woman_head_big_30.png",
	"frame": {"x":1889,"y":1,"w":150,"h":290},
	"rotated": false,
	"trimmed": false,
	"spriteSourceSize": {"x":0,"y":0,"w":150,"h":290},
	"sourceSize": {"w":150,"h":290}
},
{
	"filename": "woman_legs_big_1.png",
	"frame": {"x":1,"y":1,"w":526,"h":996},
	"rotated": false,
	"trimmed": false,
	"spriteSourceSize": {"x":0,"y":0,"w":526,"h":996},
	"sourceSize": {"w":526,"h":996}
},
{
	"filename": "woman_legs_big_4.png",
	"frame": {"x":529,"y":1,"w":535,"h":983},
	"rotated": false,
	"trimmed": false,
	"spriteSourceSize": {"x":0,"y":0,"w":535,"h":983},
	"sourceSize": {"w":535,"h":983}
},
{
	"filename": "woman_legs_big_7.png",
	"frame": {"x":544,"y":991,"w":555,"h":944},
	"rotated": false,
	"trimmed": false,
	"spriteSourceSize": {"x":0,"y":0,"w":555,"h":944},
	"sourceSize": {"w":555,"h":944}
},
{
	"filename": "woman_legs_big_11.png",
	"frame": {"x":1066,"y":1,"w":517,"h":988},
	"rotated": false,
	"trimmed": false,
	"spriteSourceSize": {"x":0,"y":0,"w":517,"h":988},
	"sourceSize": {"w":517,"h":988}
},
{
	"filename": "woman_legs_big_21.png",
	"frame": {"x":1,"y":999,"w":541,"h":959},
	"rotated": false,
	"trimmed": false,
	"spriteSourceSize": {"x":0,"y":0,"w":541,"h":959},
	"sourceSize": {"w":541,"h":959}
}],
"meta": {
	"app": "https://www.codeandweb.com/texturepacker",
	"version": "1.0",
	"image": "woman_0.png",
	"format": "RGBA8888",
	"size": {"w":2040,"h":1964},
	"scale": "1",
	"related_multi_packs": [ "woman_1.json", "woman_2.json", "woman_3.json", "woman_4.json", "woman_5.json", "woman_6.json", "woman_7.json", "woman_8.json" ],
	"smartupdate": "$TexturePacker:SmartUpdate:6d4d6bd6829c88bb830a94a472457efc:e6206b466145c302062872e90d808052:d2bb54f63532420814fa77683eb7e7f3$"
}
}
